pytest_gnupg_fixtures/__init__.py
pytest_gnupg_fixtures/fixtures.py
pytest_gnupg_fixtures/gnupg-gen-key.conf
pytest_gnupg_fixtures/utils.py
tests/__init__.py
tests/test_fixtures.py
tests/test_utils.py
pytest_gnupg_fixtures-0.1.6.dist-info/LICENSE.md
pytest_gnupg_fixtures-0.1.6.dist-info/METADATA
pytest_gnupg_fixtures-0.1.6.dist-info/WHEEL
pytest_gnupg_fixtures-0.1.6.dist-info/entry_points.txt
pytest_gnupg_fixtures-0.1.6.dist-info/top_level.txt
pytest_gnupg_fixtures-0.1.6.dist-info/RECORD
